jennie/__init__.py
jennie/responses.py
jennie/angular/__init__.py
jennie/angular/helper.py
jennie/angular/automations/__init__.py
jennie/angular/uigallery/__init__.py
jennie/api_calls/__init__.py
jennie/django/__init__.py
jennie/filehandler/__init__.py
jennie/setup/__init__.py
jennie/userinput/__init__.py
py_jennie-0.0.2.dist-info/LICENSE.txt
py_jennie-0.0.2.dist-info/METADATA
py_jennie-0.0.2.dist-info/WHEEL
py_jennie-0.0.2.dist-info/entry_points.txt
py_jennie-0.0.2.dist-info/top_level.txt
py_jennie-0.0.2.dist-info/RECORD
