Metadata-Version: 2.1
Name: py-jennie
Version: 0.0.2
Summary: The package targets protocol for uploading and reusing task and libraries
Home-page: https://github.com/Ask-Jennie/py-jennie
Author: Saurabh Pandey
Author-email: saurabh@ask-jennie.com
License: UNKNOWN
Platform: UNKNOWN
Classifier: Programming Language :: Python :: 3
Classifier: License :: OSI Approved :: MIT License
Classifier: Operating System :: OS Independent
License-File: LICENSE.txt
Requires-Dist: requests
